texthold/__init__.py
texthold/core/__init__.py
texthold/tests/__init__.py
texthold/tests/test_0.py
texthold/tests/test_1.py
texthold-1.0.1.dist-info/licenses/LICENSE.txt
texthold-1.0.1.dist-info/METADATA
texthold-1.0.1.dist-info/WHEEL
texthold-1.0.1.dist-info/top_level.txt
texthold-1.0.1.dist-info/RECORD
