Metadata-Version: 2.4
Name: texthold
Version: 1.0.1
Summary: This project provides a class that holds text.
Author-email: Johannes <johannes.programming@gmail.com>
License: The MIT License (MIT)
Project-URL: Download, https://pypi.org/project/texthold/#files
Project-URL: Index, https://pypi.org/project/texthold/
Project-URL: Source, https://github.com/johannes-programming/texthold/
Project-URL: Website, https://texthold.johannes-programming.online/
Classifier: Development Status :: 5 - Production/Stable
Classifier: License :: OSI Approved :: MIT License
Classifier: Natural Language :: English
Classifier: Operating System :: OS Independent
Classifier: Programming Language :: Python
Classifier: Programming Language :: Python :: 3
Classifier: Programming Language :: Python :: 3 :: Only
Classifier: Typing :: Typed
Requires-Python: >=3.11
License-File: LICENSE.txt
Requires-Dist: datahold<2,>=1.1.10
Dynamic: license-file
